ovos_flashrank_solver/__init__.py
ovos_flashrank_solver/version.py
ovos_flashrank_reranker_plugin-0.0.0.dist-info/METADATA
ovos_flashrank_reranker_plugin-0.0.0.dist-info/WHEEL
ovos_flashrank_reranker_plugin-0.0.0.dist-info/entry_points.txt
ovos_flashrank_reranker_plugin-0.0.0.dist-info/top_level.txt
ovos_flashrank_reranker_plugin-0.0.0.dist-info/zip-safe
ovos_flashrank_reranker_plugin-0.0.0.dist-info/RECORD
