Metadata-Version: 2.1
Name: ovos-flashrank-reranker-plugin
Version: 0.0.0
Summary: A question solver plugin for OVOS
Home-page: https://github.com/TigreGotico/ovos-flashrank-reranker-plugin
Author: jarbasai
Author-email: jarbasai@mailfence.com
License: MIT
Keywords: OVOS openvoiceos plugin utterance fallback query
Platform: UNKNOWN
Requires-Dist: ovos-plugin-manager
Requires-Dist: flashrank>=0.2.8
